cpu_files/PC.v
module PC (

    input logic clk,
    input logic rst,

    input logic[31:0] PC_JVal,
    input logic jump_en,
    input logic branch_en,
    input logic PC_Stall,

    output logic [31:0] PC_Out,
    output logic fetch_stall,

    output logic active

);

// Active is completely dependent on the value of the PC.

// JUMP_EN --> PC = JVAL
// BRANCH_EN --> PC = PC + JVAL
// PC_Stall --> PC = PC

logic [31:0] PC;
logic [31:0] branchSignExt;
logic start;

assign fetch_stall = PC_Stall;
assign active = (PC != 0) ? 1 : 0;
assign branchSignExt = (PC_JVal[15] == 1) ? {16'hFFFF, PC_JVal[15:0]} : {16'h0000, PC_JVal[15:0]};

assign PC_Out = (active == 0) ? 0 : ( (PC_Stall == 1) ? PC : ( (jump_en == 1) ? PC_JVal : ( (branch_en == 1) ? PC + branchSignExt : PC + 4 ) ) );

initial begin

    start = 0;
    PC = 0;

end

always @ (posedge clk) begin

    if (rst) begin
        start <= 1;
    end 
    else if (active) begin
        PC <= PC_Out;
    end

end

always @ (negedge rst) begin

   if (start) begin
       PC <= 32'hBFBFFFFC;
       start <= 0;
   end 
end

endmodule

cpu_files/PC_TB.v
module PC_TB ();

    logic clk;
    logic rst;

    logic[31:0] PC_JVal;
    logic jump_en;
    logic branch_en;
    logic PC_Stall;

    logic [31:0] PC_Out;
    logic fetch_stall;
    logic active;

    initial begin

        $dumpfile("PC_TB.vcd");
        $dumpvars(0, PC_TB);

        clk = 0;
        jump_en = 0;
        PC_Stall = 0;
        branch_en = 0;
        rst = 0;
        
        repeat(100) begin
            #50; clk = ~clk;
        end

        $fatal(1, "Timeout");

    end

    initial begin
        
        @ (posedge clk);
        @ (posedge clk);
        @ (posedge clk);
        rst = 1;
        @ (posedge clk);
        @ (posedge clk);
        @ (posedge clk);
         rst = 0;
        @ (posedge clk);
        @ (posedge clk);
        @ (posedge clk);
        @ (posedge clk);
        PC_Stall = 1;
        @ (posedge clk);
        @ (posedge clk);
        @ (posedge clk);
        PC_Stall = 0;
        @ (posedge clk);
        @ (posedge clk);
        @ (posedge clk);
        PC_JVal = 32'h00000010;
        branch_en = 1;
        @ (posedge clk);
        branch_en = 0;
        @ (posedge clk);
        @ (posedge clk);
        @ (posedge clk);
        PC_JVal = 32'h0000FFF4;
        branch_en = 1;
        @ (posedge clk);
        branch_en = 0;
        @ (posedge clk);
        @ (posedge clk);
        PC_JVal = 0;
        jump_en = 1;
        @ (posedge clk);
        jump_en = 0;
        @ (posedge clk);
        @ (posedge clk);
        @ (posedge clk);
    end

    PC PC(.clk(clk), .rst(rst), .PC_JVal(PC_JVal), .jump_en(jump_en), .branch_en(branch_en), .PC_Stall(PC_Stall), .PC_Out(PC_Out), .fetch_stall(fetch_stall), .active(active));

endmodule

cpu_files/PC_TB.vcd
$date
	Fri Dec 31 14:58:03 2021
$end
$version
	Icarus Verilog
$end
$timescale
	1s
$end
$scope module PC_TB $end
$var wire 1 ! fetch_stall $end
$var wire 1 " active $end
$var wire 32 # PC_Out [31:0] $end
$var reg 32 $ PC_JVal [31:0] $end
$var reg 1 % PC_Stall $end
$var reg 1 & branch_en $end
$var reg 1 ' clk $end
$var reg 1 ( jump_en $end
$var reg 1 ) rst $end
$scope module PC $end
$var wire 32 * PC_JVal [31:0] $end
$var wire 1 % PC_Stall $end
$var wire 1 & branch_en $end
$var wire 1 ' clk $end
$var wire 1 ! fetch_stall $end
$var wire 1 ( jump_en $end
$var wire 1 ) rst $end
$var wire 32 + branchSignExt [31:0] $end
$var wire 1 " active $end
$var wire 32 , PC_Out [31:0] $end
$var reg 32 - PC [31:0] $end
$var reg 1 . start $end
$upscope $end
$upscope $end
$enddefinitions $end
#0
$dumpvars
0.
b0 -
b0 ,
bx +
bx *
0)
0(
0'
0&
0%
bx $
b0 #
0"
0!
$end
#50
1'
#100
0'
#150
1'
#200
0'
#250
1.
1)
1'
#300
0'
#350
1'
#400
0'
#450
1'
#500
0'
#550
b10111111110000000000000000000000 #
b10111111110000000000000000000000 ,
1"
0.
b10111111101111111111111111111100 -
0)
1'
#600
0'
#650
b10111111110000000000000000000100 #
b10111111110000000000000000000100 ,
b10111111110000000000000000000000 -
1'
#700
0'
#750
b10111111110000000000000000001000 #
b10111111110000000000000000001000 ,
b10111111110000000000000000000100 -
1'
#800
0'
#850
b10111111110000000000000000001100 #
b10111111110000000000000000001100 ,
b10111111110000000000000000001000 -
1'
#900
0'
#950
b10111111110000000000000000001100 -
b10111111110000000000000000001100 #
b10111111110000000000000000001100 ,
1!
1%
1'
#1000
0'
#1050
1'
#1100
0'
#1150
1'
#1200
0'
#1250
b10111111110000000000000000010000 #
b10111111110000000000000000010000 ,
0!
0%
1'
#1300
0'
#1350
b10111111110000000000000000010100 #
b10111111110000000000000000010100 ,
b10111111110000000000000000010000 -
1'
#1400
0'
#1450
b10111111110000000000000000011000 #
b10111111110000000000000000011000 ,
b10111111110000000000000000010100 -
1'
#1500
0'
#1550
b10111111110000000000000000011000 -
b10111111110000000000000000101000 #
b10111111110000000000000000101000 ,
b10000 +
1&
b10000 $
b10000 *
1'
#1600
0'
#1650
b10111111110000000000000000101000 -
b10111111110000000000000000101100 #
b10111111110000000000000000101100 ,
0&
1'
#1700
0'
#1750
b10111111110000000000000000110000 #
b10111111110000000000000000110000 ,
b10111111110000000000000000101100 -
1'
#1800
0'
#1850
b10111111110000000000000000110100 #
b10111111110000000000000000110100 ,
b10111111110000000000000000110000 -
1'
#1900
0'
#1950
b10111111110000000000000000110100 -
b10111111110000000000000000101000 #
b10111111110000000000000000101000 ,
b11111111111111111111111111110100 +
1&
b1111111111110100 $
b1111111111110100 *
1'
#2000
0'
#2050
b10111111110000000000000000101000 -
b10111111110000000000000000101100 #
b10111111110000000000000000101100 ,
0&
1'
#2100
0'
#2150
b10111111110000000000000000110000 #
b10111111110000000000000000110000 ,
b10111111110000000000000000101100 -
1'
#2200
0'
#2250
b10111111110000000000000000110000 -
b0 #
b0 ,
b0 +
1(
b0 $
b0 *
1'
#2300
0'
#2350
0"
b0 -
b0 #
b0 ,
0(
1'
