cpu_files/PC.v
module PC (

    input logic clk,
    input logic rst,

    input logic[31:0] PC_JVal,
    input logic jump_en,
    input logic branch_en,
    input logic PC_Stall,

    output logic [31:0] PC_Out,
    output logic fetch_stall,

    output logic active,
    output logic [2:0] check

);

// Active is completely dependent on the value of the PC.

// JUMP_EN --> PC = JVAL
// BRANCH_EN --> PC = PC + JVAL
// PC_Stall --> PC = PC

reg [31:0] PC;
logic [31:0] branchSignExt = (PC_JVal[15] == 1) ? {16'hFFFF, PC_JVal[15:0]} : {16'h0000, PC_JVal[15:0]};
logic start;

assign fetch_stall = PC_Stall;
assign active = (PC != 0) ? 1 : 0;

assign PC_Out = (active == 0) ? 0 : ( (PC_Stall == 1) ? PC + 4 : ( (jump_en == 1) ? PC_JVal : ( (branch_en == 1) ? PC + branchSignExt : PC + 4 ) ) );

initial begin

    PC = 0;
    start = 0;

    check = 0;

end

always_ff @ (posedge clk) begin

    check[1] <= ~check[1];

    if (rst) begin
        start <= 1;
    end 
    else if (active) begin

        
        
        if (PC_Stall) begin
            PC <= PC;
            check[0] <= ~check[0];
        end
        else if (jump_en) begin
            PC <= PC_JVal;
        end
        else if (branch_en) begin
            PC <= PC + branchSignExt;
        end
        else begin
            PC <= PC + 4;
        end
        
    end

end

always_ff @ (negedge rst) begin
    if (start) begin
        PC <= 32'hBFBFFFFC;
        start <= 0;
    end
end

endmodule

cpu_files/PC_TB.v
module PC_TB ();

    logic clk;
    logic rst;

    logic[31:0] PC_JVal;
    logic jump_en;
    logic branch_en;
    logic PC_Stall;

    logic [31:0] PC_Out;
    logic fetch_stall;
    logic active;
    logic [2:0] check;

    initial begin

        $dumpfile("PC_TB.vcd");
        $dumpvars(0, PC_TB);

        clk = 0;
        jump_en = 0;
        PC_Stall = 0;
        branch_en = 0;
        rst = 0;
        
        repeat(100) begin
            #50; clk = ~clk;
        end

        $fatal(1, "Timeout");

    end

    initial begin
        
        @ (posedge clk);
        @ (posedge clk);
        @ (posedge clk);
        rst = 1;
        @ (posedge clk);
        @ (posedge clk);
        @ (posedge clk);
         rst = 0;
        @ (posedge clk);
        @ (posedge clk);
         @ (posedge clk);
        
        @ (posedge clk);
        PC_Stall = 1;
        @ (posedge clk);
        PC_Stall = 0;
        @ (posedge clk);
        
        

    end

    PC PC(.clk(clk), .rst(rst), .PC_JVal(PC_JVal), .jump_en(jump_en), .branch_en(branch_en), .PC_Stall(PC_Stall), .PC_Out(PC_Out), .fetch_stall(fetch_stall), .active(active), .check(check));

endmodule

cpu_files/PC_TB.vcd
$date
	Fri Dec 31 01:01:12 2021
$end
$version
	Icarus Verilog
$end
$timescale
	1s
$end
$scope module PC_TB $end
$var wire 1 ! fetch_stall $end
$var wire 3 " check [2:0] $end
$var wire 1 # active $end
$var wire 32 $ PC_Out [31:0] $end
$var reg 32 % PC_JVal [31:0] $end
$var reg 1 & PC_Stall $end
$var reg 1 ' branch_en $end
$var reg 1 ( clk $end
$var reg 1 ) jump_en $end
$var reg 1 * rst $end
$scope module PC $end
$var wire 32 + PC_JVal [31:0] $end
$var wire 1 & PC_Stall $end
$var wire 1 ' branch_en $end
$var wire 1 ( clk $end
$var wire 1 ! fetch_stall $end
$var wire 1 ) jump_en $end
$var wire 1 * rst $end
$var wire 1 # active $end
$var wire 32 , PC_Out [31:0] $end
$var reg 32 - PC [31:0] $end
$var reg 32 . branchSignExt [31:0] $end
$var reg 3 / check [2:0] $end
$var reg 1 0 start $end
$upscope $end
$upscope $end
$enddefinitions $end
#0
$dumpvars
00
b0 /
bx .
b0 -
b0 ,
bx +
0*
0)
0(
0'
0&
bx %
b0 $
0#
b0 "
0!
$end
#50
b10 "
b10 /
1(
#100
0(
#150
b0 "
b0 /
1(
#200
0(
#250
10
b10 "
b10 /
1*
1(
#300
0(
#350
b0 "
b0 /
1(
#400
0(
#450
b10 "
b10 /
1(
#500
0(
#550
b10111111110000000000000000000000 $
b10111111110000000000000000000000 ,
1#
00
b10111111101111111111111111111100 -
b0 "
b0 /
0*
1(
#600
0(
#650
b10111111110000000000000000000100 $
b10111111110000000000000000000100 ,
b10111111110000000000000000000000 -
b10 "
b10 /
1(
#700
0(
#750
b10111111110000000000000000001000 $
b10111111110000000000000000001000 ,
b10111111110000000000000000000100 -
b0 "
b0 /
1(
#800
0(
#850
b10111111110000000000000000001100 $
b10111111110000000000000000001100 ,
b10111111110000000000000000001000 -
b10 "
b10 /
1(
#900
0(
#950
b10111111110000000000000000010000 $
b10111111110000000000000000010000 ,
b10111111110000000000000000001100 -
b0 "
b0 /
1!
1&
1(
#1000
0(
#1050
b10111111110000000000000000010100 $
b10111111110000000000000000010100 ,
b10111111110000000000000000010000 -
b10 "
b10 /
0!
0&
1(
#1100
0(
#1150
b10111111110000000000000000011000 $
b10111111110000000000000000011000 ,
b10111111110000000000000000010100 -
b0 "
b0 /
1(
#1200
0(
#1250
b10111111110000000000000000011100 $
b10111111110000000000000000011100 ,
b10111111110000000000000000011000 -
b10 "
b10 /
1(
#1300
0(
#1350
b10111111110000000000000000100000 $
b10111111110000000000000000100000 ,
b10111111110000000000000000011100 -
b0 "
b0 /
1(
#1400
0(
#1450
b10111111110000000000000000100100 $
b10111111110000000000000000100100 ,
b10111111110000000000000000100000 -
b10 "
b10 /
1(
#1500
0(
#1550
b10111111110000000000000000101000 $
b10111111110000000000000000101000 ,
b10111111110000000000000000100100 -
b0 "
b0 /
1(
#1600
0(
#1650
b10111111110000000000000000101100 $
b10111111110000000000000000101100 ,
b10111111110000000000000000101000 -
b10 "
b10 /
1(
#1700
0(
#1750
b10111111110000000000000000110000 $
b10111111110000000000000000110000 ,
b10111111110000000000000000101100 -
b0 "
b0 /
1(
#1800
0(
#1850
b10111111110000000000000000110100 $
b10111111110000000000000000110100 ,
b10111111110000000000000000110000 -
b10 "
b10 /
1(
#1900
0(
#1950
b10111111110000000000000000111000 $
b10111111110000000000000000111000 ,
b10111111110000000000000000110100 -
b0 "
b0 /
1(
#2000
0(
#2050
b10111111110000000000000000111100 $
b10111111110000000000000000111100 ,
b10111111110000000000000000111000 -
b10 "
b10 /
1(
#2100
0(
#2150
b10111111110000000000000001000000 $
b10111111110000000000000001000000 ,
b10111111110000000000000000111100 -
b0 "
b0 /
1(
#2200
0(
#2250
b10111111110000000000000001000100 $
b10111111110000000000000001000100 ,
b10111111110000000000000001000000 -
b10 "
b10 /
1(
#2300
0(
#2350
b10111111110000000000000001001000 $
b10111111110000000000000001001000 ,
b10111111110000000000000001000100 -
b0 "
b0 /
1(
#2400
0(
#2450
b10111111110000000000000001001100 $
b10111111110000000000000001001100 ,
b10111111110000000000000001001000 -
b10 "
b10 /
1(
#2500
0(
#2550
b10111111110000000000000001010000 $
b10111111110000000000000001010000 ,
b10111111110000000000000001001100 -
b0 "
b0 /
1(
#2600
0(
#2650
b10111111110000000000000001010100 $
b10111111110000000000000001010100 ,
b10111111110000000000000001010000 -
b10 "
b10 /
1(
#2700
0(
#2750
b10111111110000000000000001011000 $
b10111111110000000000000001011000 ,
b10111111110000000000000001010100 -
b0 "
b0 /
1(
#2800
0(
#2850
b10111111110000000000000001011100 $
b10111111110000000000000001011100 ,
b10111111110000000000000001011000 -
b10 "
b10 /
1(
#2900
0(
#2950
b10111111110000000000000001100000 $
b10111111110000000000000001100000 ,
b10111111110000000000000001011100 -
b0 "
b0 /
1(
#3000
0(
#3050
b10111111110000000000000001100100 $
b10111111110000000000000001100100 ,
b10111111110000000000000001100000 -
b10 "
b10 /
1(
#3100
0(
#3150
b10111111110000000000000001101000 $
b10111111110000000000000001101000 ,
b10111111110000000000000001100100 -
b0 "
b0 /
1(
#3200
0(
#3250
b10111111110000000000000001101100 $
b10111111110000000000000001101100 ,
b10111111110000000000000001101000 -
b10 "
b10 /
1(
#3300
0(
#3350
b10111111110000000000000001110000 $
b10111111110000000000000001110000 ,
b10111111110000000000000001101100 -
b0 "
b0 /
1(
#3400
0(
#3450
b10111111110000000000000001110100 $
b10111111110000000000000001110100 ,
b10111111110000000000000001110000 -
b10 "
b10 /
1(
#3500
0(
#3550
b10111111110000000000000001111000 $
b10111111110000000000000001111000 ,
b10111111110000000000000001110100 -
b0 "
b0 /
1(
#3600
0(
#3650
b10111111110000000000000001111100 $
b10111111110000000000000001111100 ,
b10111111110000000000000001111000 -
b10 "
b10 /
1(
#3700
0(
#3750
b10111111110000000000000010000000 $
b10111111110000000000000010000000 ,
b10111111110000000000000001111100 -
b0 "
b0 /
1(
#3800
0(
#3850
b10111111110000000000000010000100 $
b10111111110000000000000010000100 ,
b10111111110000000000000010000000 -
b10 "
b10 /
1(
#3900
0(
#3950
b10111111110000000000000010001000 $
b10111111110000000000000010001000 ,
b10111111110000000000000010000100 -
b0 "
b0 /
1(
#4000
0(
#4050
b10111111110000000000000010001100 $
b10111111110000000000000010001100 ,
b10111111110000000000000010001000 -
b10 "
b10 /
1(
#4100
0(
#4150
b10111111110000000000000010010000 $
b10111111110000000000000010010000 ,
b10111111110000000000000010001100 -
b0 "
b0 /
1(
#4200
0(
#4250
b10111111110000000000000010010100 $
b10111111110000000000000010010100 ,
b10111111110000000000000010010000 -
b10 "
b10 /
1(
#4300
0(
#4350
b10111111110000000000000010011000 $
b10111111110000000000000010011000 ,
b10111111110000000000000010010100 -
b0 "
b0 /
1(
#4400
0(
#4450
b10111111110000000000000010011100 $
b10111111110000000000000010011100 ,
b10111111110000000000000010011000 -
b10 "
b10 /
1(
#4500
0(
#4550
b10111111110000000000000010100000 $
b10111111110000000000000010100000 ,
b10111111110000000000000010011100 -
b0 "
b0 /
1(
#4600
0(
#4650
b10111111110000000000000010100100 $
b10111111110000000000000010100100 ,
b10111111110000000000000010100000 -
b10 "
b10 /
1(
#4700
0(
#4750
b10111111110000000000000010101000 $
b10111111110000000000000010101000 ,
b10111111110000000000000010100100 -
b0 "
b0 /
1(
#4800
0(
#4850
b10111111110000000000000010101100 $
b10111111110000000000000010101100 ,
b10111111110000000000000010101000 -
b10 "
b10 /
1(
#4900
0(
#4950
b10111111110000000000000010110000 $
b10111111110000000000000010110000 ,
b10111111110000000000000010101100 -
b0 "
b0 /
1(
