cpu_files/PC.v
module PC (

    input logic clk,
    input logic rst,

    input logic[31:0] PC_JVal,
    input logic jump_en,
    input logic branch_en,
    input logic PC_Stall,

    output logic [31:0] PC_Out,
    output logic fetch_stall,

    output logic active

);

// Active is completely dependent on the value of the PC.

// JUMP_EN --> PC = JVAL
// BRANCH_EN --> PC = PC + JVAL
// PC_Stall --> PC = PC

reg [31:0] PC;
logic [31:0] branchSignExt = (PC_JVal[15] == 1) ? {16'hFFFF, PC_JVal[15:0]} : {16'h0000, PC_JVal[15:0]};

assign fetch_stall = PC_Stall;
assign active = (PC != 0) ? 1 : 0;

assign PC_Out = (active == 0 || rst == 1) ? 0 : ( (PC_Stall == 1) ? PC + 4 : ( (jump_en == 1) ? PC_JVal : ( (branch_en == 1) ? PC + branchSignExt : PC + 4 ) ) );

initial begin

    PC = 0;

end

always_ff @ (posedge clk) begin

    if (rst) begin
        PC <= 32'hBFBFFFFC;
    end 
    else if (active) begin
        
        if (PC_Stall) begin
            PC <= PC;
        end
        else if (jump_en) begin
            PC <= PC_JVal;
        end
        else if (branch_en) begin
            PC <= PC + branchSignExt;
        end
        else begin
            PC <= PC + 4;
        end

    end

end

endmodule

cpu_files/PC_TB.v
module PC_TB ();

    logic clk;
    logic rst;

    logic[31:0] PC_JVal;
    logic jump_en;
    logic branch_en;
    logic PC_Stall;

    logic [31:0] PC_Out;
    logic fetch_stall;
    logic active;

    initial begin

        $dumpfile("PC_TB.vcd");
        $dumpvars(0, PC_TB);

        clk = 0;
        jump_en = 0;
        PC_Stall = 0;
        branch_en = 0;
        
        repeat(100) begin
            #10; clk = ~clk;
        end

        $fatal(1, "Timeout");

    end

    initial begin
        
        @ (posedge clk);
        @ (posedge clk);
        @ (posedge clk);
        rst = 1;
        @ (posedge clk);
        rst = 0;
        @ (posedge clk);
        @ (posedge clk);
        @ (posedge clk);
        PC_Stall = 1;
        @ (posedge clk);
        @ (posedge clk);
        @ (posedge clk);
        PC_Stall = 0;

    end

    PC PC(clk, rst, PC_JVal, jump_en, branch_en, PC_Stall, PC_Out, fetch_stall, active);

endmodule

cpu_files/PC_TB.vcd
$date
	Thu Dec 30 21:26:19 2021
$end
$version
	Icarus Verilog
$end
$timescale
	1s
$end
$scope module PC_TB $end
$var wire 1 ! fetch_stall $end
$var wire 1 " active $end
$var wire 32 # PC_Out [31:0] $end
$var reg 32 $ PC_JVal [31:0] $end
$var reg 1 % PC_Stall $end
$var reg 1 & branch_en $end
$var reg 1 ' clk $end
$var reg 1 ( jump_en $end
$var reg 1 ) rst $end
$scope module PC $end
$var wire 32 * PC_JVal [31:0] $end
$var wire 1 % PC_Stall $end
$var wire 1 & branch_en $end
$var wire 1 ' clk $end
$var wire 1 ! fetch_stall $end
$var wire 1 ( jump_en $end
$var wire 1 ) rst $end
$var wire 1 " active $end
$var wire 32 + PC_Out [31:0] $end
$var reg 32 , PC [31:0] $end
$var reg 32 - branchSignExt [31:0] $end
$upscope $end
$upscope $end
$enddefinitions $end
#0
$dumpvars
bx -
b0 ,
b0 +
bx *
x)
0(
0'
0&
0%
bx $
b0 #
0"
0!
$end
#10
1'
#20
0'
#30
1'
#40
0'
#50
1"
b10111111101111111111111111111100 ,
1)
1'
#60
0'
#70
b10111111110000000000000000000000 #
b10111111110000000000000000000000 +
0)
1'
#80
0'
#90
b10111111110000000000000000000100 #
b10111111110000000000000000000100 +
b10111111110000000000000000000000 ,
1'
#100
0'
#110
b10111111110000000000000000001000 #
b10111111110000000000000000001000 +
b10111111110000000000000000000100 ,
1'
#120
0'
#130
1!
1%
1'
#140
0'
#150
1'
#160
0'
#170
1'
#180
0'
#190
0!
0%
1'
#200
0'
#210
b10111111110000000000000000001100 #
b10111111110000000000000000001100 +
b10111111110000000000000000001000 ,
1'
#220
0'
#230
b10111111110000000000000000010000 #
b10111111110000000000000000010000 +
b10111111110000000000000000001100 ,
1'
#240
0'
#250
b10111111110000000000000000010100 #
b10111111110000000000000000010100 +
b10111111110000000000000000010000 ,
1'
#260
0'
#270
b10111111110000000000000000011000 #
b10111111110000000000000000011000 +
b10111111110000000000000000010100 ,
1'
#280
0'
#290
b10111111110000000000000000011100 #
b10111111110000000000000000011100 +
b10111111110000000000000000011000 ,
1'
#300
0'
#310
b10111111110000000000000000100000 #
b10111111110000000000000000100000 +
b10111111110000000000000000011100 ,
1'
#320
0'
#330
b10111111110000000000000000100100 #
b10111111110000000000000000100100 +
b10111111110000000000000000100000 ,
1'
#340
0'
#350
b10111111110000000000000000101000 #
b10111111110000000000000000101000 +
b10111111110000000000000000100100 ,
1'
#360
0'
#370
b10111111110000000000000000101100 #
b10111111110000000000000000101100 +
b10111111110000000000000000101000 ,
1'
#380
0'
#390
b10111111110000000000000000110000 #
b10111111110000000000000000110000 +
b10111111110000000000000000101100 ,
1'
#400
0'
#410
b10111111110000000000000000110100 #
b10111111110000000000000000110100 +
b10111111110000000000000000110000 ,
1'
#420
0'
#430
b10111111110000000000000000111000 #
b10111111110000000000000000111000 +
b10111111110000000000000000110100 ,
1'
#440
0'
#450
b10111111110000000000000000111100 #
b10111111110000000000000000111100 +
b10111111110000000000000000111000 ,
1'
#460
0'
#470
b10111111110000000000000001000000 #
b10111111110000000000000001000000 +
b10111111110000000000000000111100 ,
1'
#480
0'
#490
b10111111110000000000000001000100 #
b10111111110000000000000001000100 +
b10111111110000000000000001000000 ,
1'
#500
0'
#510
b10111111110000000000000001001000 #
b10111111110000000000000001001000 +
b10111111110000000000000001000100 ,
1'
#520
0'
#530
b10111111110000000000000001001100 #
b10111111110000000000000001001100 +
b10111111110000000000000001001000 ,
1'
#540
0'
#550
b10111111110000000000000001010000 #
b10111111110000000000000001010000 +
b10111111110000000000000001001100 ,
1'
#560
0'
#570
b10111111110000000000000001010100 #
b10111111110000000000000001010100 +
b10111111110000000000000001010000 ,
1'
#580
0'
#590
b10111111110000000000000001011000 #
b10111111110000000000000001011000 +
b10111111110000000000000001010100 ,
1'
#600
0'
#610
b10111111110000000000000001011100 #
b10111111110000000000000001011100 +
b10111111110000000000000001011000 ,
1'
#620
0'
#630
b10111111110000000000000001100000 #
b10111111110000000000000001100000 +
b10111111110000000000000001011100 ,
1'
#640
0'
#650
b10111111110000000000000001100100 #
b10111111110000000000000001100100 +
b10111111110000000000000001100000 ,
1'
#660
0'
#670
b10111111110000000000000001101000 #
b10111111110000000000000001101000 +
b10111111110000000000000001100100 ,
1'
#680
0'
#690
b10111111110000000000000001101100 #
b10111111110000000000000001101100 +
b10111111110000000000000001101000 ,
1'
#700
0'
#710
b10111111110000000000000001110000 #
b10111111110000000000000001110000 +
b10111111110000000000000001101100 ,
1'
#720
0'
#730
b10111111110000000000000001110100 #
b10111111110000000000000001110100 +
b10111111110000000000000001110000 ,
1'
#740
0'
#750
b10111111110000000000000001111000 #
b10111111110000000000000001111000 +
b10111111110000000000000001110100 ,
1'
#760
0'
#770
b10111111110000000000000001111100 #
b10111111110000000000000001111100 +
b10111111110000000000000001111000 ,
1'
#780
0'
#790
b10111111110000000000000010000000 #
b10111111110000000000000010000000 +
b10111111110000000000000001111100 ,
1'
#800
0'
#810
b10111111110000000000000010000100 #
b10111111110000000000000010000100 +
b10111111110000000000000010000000 ,
1'
#820
0'
#830
b10111111110000000000000010001000 #
b10111111110000000000000010001000 +
b10111111110000000000000010000100 ,
1'
#840
0'
#850
b10111111110000000000000010001100 #
b10111111110000000000000010001100 +
b10111111110000000000000010001000 ,
1'
#860
0'
#870
b10111111110000000000000010010000 #
b10111111110000000000000010010000 +
b10111111110000000000000010001100 ,
1'
#880
0'
#890
b10111111110000000000000010010100 #
b10111111110000000000000010010100 +
b10111111110000000000000010010000 ,
1'
#900
0'
#910
b10111111110000000000000010011000 #
b10111111110000000000000010011000 +
b10111111110000000000000010010100 ,
1'
#920
0'
#930
b10111111110000000000000010011100 #
b10111111110000000000000010011100 +
b10111111110000000000000010011000 ,
1'
#940
0'
#950
b10111111110000000000000010100000 #
b10111111110000000000000010100000 +
b10111111110000000000000010011100 ,
1'
#960
0'
#970
b10111111110000000000000010100100 #
b10111111110000000000000010100100 +
b10111111110000000000000010100000 ,
1'
#980
0'
#990
b10111111110000000000000010101000 #
b10111111110000000000000010101000 +
b10111111110000000000000010100100 ,
1'
